CHANGES.txt
COPYRIGHT.txt
LICENSE.txt
README.txt
TODO.txt
bootstrap.py
buildout.cfg
setup.py
src/zodbupgrade/__init__.py
src/zodbupgrade/analyze.py
src/zodbupgrade/main.py
src/zodbupgrade/tests.py
src/zodbupgrade.egg-info/PKG-INFO
src/zodbupgrade.egg-info/SOURCES.txt
src/zodbupgrade.egg-info/dependency_links.txt
src/zodbupgrade.egg-info/entry_points.txt
src/zodbupgrade.egg-info/requires.txt
src/zodbupgrade.egg-info/top_level.txt