Metadata-Version: 1.0
Name: zodbupgrade
Version: 0.1
Summary: Update ZODB class references for moved or renamed classes.
Home-page: http://www.python.org/pypi/zodbupgrade
Author: Zope Developers
Author-email: zodb-dev@zope.org
License: ZPL 2.1
Platform: UNKNOWN
